IMALogger/IMALogger.py
IMALogger/__init__.py
IMALogger-0.0.5.dist-info/LICENSE
IMALogger-0.0.5.dist-info/METADATA
IMALogger-0.0.5.dist-info/WHEEL
IMALogger-0.0.5.dist-info/top_level.txt
IMALogger-0.0.5.dist-info/RECORD
